data_pipeline/__init__.py
data_pipeline/__main__.py
data_pipeline/aisr/__init__.py
data_pipeline/aisr/actions.py
data_pipeline/aisr/authenticate.py
data_pipeline/cli.py
data_pipeline/etl_workflow.py
data_pipeline/extract.py
data_pipeline/load.py
data_pipeline/log_analyzer.py
data_pipeline/metadata_generator.py
data_pipeline/pipeline_factory.py
data_pipeline/transform.py
minnesota_immunization_data_pipeline-0.3.0.dist-info/METADATA
minnesota_immunization_data_pipeline-0.3.0.dist-info/WHEEL
minnesota_immunization_data_pipeline-0.3.0.dist-info/entry_points.txt
minnesota_immunization_data_pipeline-0.3.0.dist-info/RECORD
